ovos_PHAL_plugin_network_manager/__init__.py
ovos_PHAL_plugin_network_manager/gui.py
ovos_PHAL_plugin_network_manager/version.py
ovos_PHAL_plugin_network_manager/gui/qt5/BottomActionButton.qml
ovos_PHAL_plugin_network_manager/gui/qt5/GuiClientLoader.qml
ovos_PHAL_plugin_network_manager/gui/qt5/ManageConnectedNetwork.qml
ovos_PHAL_plugin_network_manager/gui/qt5/ManageUnconnectedNetwork.qml
ovos_PHAL_plugin_network_manager/gui/qt5/ModeChoose.qml
ovos_PHAL_plugin_network_manager/gui/qt5/NetworkingLoader.qml
ovos_PHAL_plugin_network_manager/gui/qt5/Status.qml
ovos_PHAL_plugin_network_manager/gui/qt5/ViewPod.qml
ovos_PHAL_plugin_network_manager/gui/qt5/icons/check-circle.svg
ovos_PHAL_plugin_network_manager/gui/qt5/icons/info-circle.svg
ovos_PHAL_plugin_network_manager/gui/qt5/icons/ondisplay.svg
ovos_PHAL_plugin_network_manager/gui/qt5/icons/onmobile.svg
ovos_PHAL_plugin_network_manager/gui/qt5/icons/times-circle.svg
ovos_PHAL_plugin_network_manager/gui/qt5/networking/Connecting.qml
ovos_PHAL_plugin_network_manager/gui/qt5/networking/NetworkItem.qml
ovos_PHAL_plugin_network_manager/gui/qt5/networking/NetworkItemParent.qml
ovos_PHAL_plugin_network_manager/gui/qt5/networking/NetworkItemSetting.qml
ovos_PHAL_plugin_network_manager/gui/qt5/networking/SelectNetwork.qml
ovos_PHAL_plugin_network_manager/gui/qt5/networking/animations/connecting.json
ovos_PHAL_plugin_network_manager/gui/qt5/networking/animations/fail.json
ovos_PHAL_plugin_network_manager/gui/qt5/networking/animations/security.json
ovos_PHAL_plugin_network_manager/gui/qt5/networking/animations/success.json
ovos_PHAL_plugin_network_manager/gui/qt5/sounds/ui_sounds_clicked.wav
ovos_PHAL_plugin_network_manager-1.3.4.dist-info/LICENSE
ovos_PHAL_plugin_network_manager-1.3.4.dist-info/METADATA
ovos_PHAL_plugin_network_manager-1.3.4.dist-info/WHEEL
ovos_PHAL_plugin_network_manager-1.3.4.dist-info/entry_points.txt
ovos_PHAL_plugin_network_manager-1.3.4.dist-info/top_level.txt
ovos_PHAL_plugin_network_manager-1.3.4.dist-info/zip-safe
ovos_PHAL_plugin_network_manager-1.3.4.dist-info/RECORD
