Metadata-Version: 2.1
Name: ovos-PHAL-plugin-network-manager
Version: 1.3.4
Summary: Network Manager plugin for OpenVoiceOS hardware abstraction layer
Home-page: https://github.com/OpenVoiceOS/ovos-PHAL-plugin-network-manager
Author: Aiix
Author-email: aix.m@outlook.com
License: Apache-2.0
Platform: UNKNOWN
Classifier: Development Status :: 3 - Alpha
Classifier: Intended Audience :: Developers
Classifier: Topic :: System :: Networking
Classifier: License :: OSI Approved :: Apache Software License
Classifier: Programming Language :: Python :: 3.5
Classifier: Programming Language :: Python :: 3.6
Classifier: Programming Language :: Python :: 3.7
Classifier: Programming Language :: Python :: 3.8
Classifier: Programming Language :: Python :: 3.9
Classifier: Programming Language :: Python :: 3.10
Requires-Dist: ovos-plugin-manager<1.0.0,>=0.0.22
Requires-Dist: ovos-utils<1.0.0,>=0.0.32
Requires-Dist: ovos-bus-client<2.0.0,>=0.0.3
Requires-Dist: dbus-next
